hkube_websocket_client-0.56.1.data/scripts/wsdump.py
websocket/__init__.py
websocket/_abnf.py
websocket/_app.py
websocket/_cookiejar.py
websocket/_core.py
websocket/_exceptions.py
websocket/_handshake.py
websocket/_http.py
websocket/_logging.py
websocket/_socket.py
websocket/_ssl_compat.py
websocket/_url.py
websocket/_utils.py
websocket/tests/__init__.py
websocket/tests/test_cookiejar.py
websocket/tests/test_websocket.py
websocket/tests/data/header01.txt
websocket/tests/data/header02.txt
hkube_websocket_client-0.56.1.dist-info/LICENSE
hkube_websocket_client-0.56.1.dist-info/METADATA
hkube_websocket_client-0.56.1.dist-info/WHEEL
hkube_websocket_client-0.56.1.dist-info/top_level.txt
hkube_websocket_client-0.56.1.dist-info/RECORD
