Metadata-Version: 2.1
Name: hkube-websocket-client
Version: 0.56.1
Summary: Fork of WebSocket client for Python. Fixes send performance issues with large data payload
Home-page: https://github.com/kube-HPC/websocket-client.git
Author: liris/hkube
Author-email: liris.pp@gmail.com
License: BSD
Keywords: websockets
Platform: UNKNOWN
Classifier: Development Status :: 4 - Beta
Classifier: License :: OSI Approved :: BSD License
Classifier: Programming Language :: Python
Classifier: Programming Language :: Python :: 2
Classifier: Programming Language :: Python :: 2.6
Classifier: Programming Language :: Python :: 2.7
Classifier: Programming Language :: Python :: 3
Classifier: Programming Language :: Python :: 3.4
Classifier: Programming Language :: Python :: 3.5
Classifier: Programming Language :: Python :: 3.6
Classifier: Programming Language :: Python :: 3.7
Classifier: Operating System :: MacOS :: MacOS X
Classifier: Operating System :: POSIX
Classifier: Operating System :: Microsoft :: Windows
Classifier: Topic :: Internet
Classifier: Topic :: Software Development :: Libraries :: Python Modules
Classifier: Intended Audience :: Developers
Requires-Python: >=2.6, !=3.0.*, !=3.1.*, !=3.2.*, !=3.3.*
Requires-Dist: six
